read_roi/__init__.py
read_roi/_read_roi.py
read_roi/_version.py
read_roi-1.4.2.dist-info/DESCRIPTION.rst
read_roi-1.4.2.dist-info/METADATA
read_roi-1.4.2.dist-info/RECORD
read_roi-1.4.2.dist-info/WHEEL
read_roi-1.4.2.dist-info/metadata.json
read_roi-1.4.2.dist-info/top_level.txt
