Metadata-Version: 2.0
Name: read-roi
Version: 1.4.2
Summary: Read ROI files .zip or .roi generated with ImageJ.
Home-page: https://github.com/hadim/read-roi/
Author: Hadrien Mary
Author-email: hadrien.mary@gmail.com
License: UNKNOWN
Platform: UNKNOWN
Classifier: Development Status :: 5 - Production/Stable
Classifier: Intended Audience :: Developers
Classifier: Natural Language :: English
Classifier: License :: OSI Approved :: BSD License
Classifier: Operating System :: OS Independent
Classifier: Programming Language :: Python
Classifier: Programming Language :: Python :: 3
